{
  "hash": "e246e8a8",
  "browserHash": "8e584817",
  "optimized": {
    "@vue/devtools-api": {
      "src": "../../../../node_modules/@vue/devtools-api/lib/esm/index.js",
      "file": "@vue_devtools-api.js",
      "fileHash": "b3d283f6",
      "needsInterop": false
    },
    "@vuepress/shared": {
      "src": "../../../../node_modules/@vuepress/shared/dist/index.js",
      "file": "@vuepress_shared.js",
      "fileHash": "d04c829d",
      "needsInterop": false
    },
    "vue": {
      "src": "../../../../node_modules/vue/dist/vue.runtime.esm-bundler.js",
      "file": "vue.js",
      "fileHash": "210651ea",
      "needsInterop": false
    },
    "vue-router": {
      "src": "../../../../node_modules/vue-router/dist/vue-router.esm-bundler.js",
      "file": "vue-router.js",
      "fileHash": "28d10de7",
      "needsInterop": false
    },
    "@vueuse/core": {
      "src": "../../../../node_modules/@vueuse/core/index.mjs",
      "file": "@vueuse_core.js",
      "fileHash": "f939fdeb",
      "needsInterop": false
    },
    "autosize": {
      "src": "../../../../node_modules/autosize/dist/autosize.esm.js",
      "file": "autosize.js",
      "fileHash": "843ef0f3",
      "needsInterop": false
    },
    "register-service-worker": {
      "src": "../../../../node_modules/register-service-worker/index.js",
      "file": "register-service-worker.js",
      "fileHash": "5a3b7b1d",
      "needsInterop": false
    }
  },
  "chunks": {
    "chunk-EQZ2CAY2": {
      "file": "chunk-EQZ2CAY2.js"
    },
    "chunk-XLFQFOPK": {
      "file": "chunk-XLFQFOPK.js"
    },
    "chunk-UBHBAAEW": {
      "file": "chunk-UBHBAAEW.js"
    },
    "chunk-667QNQL3": {
      "file": "chunk-667QNQL3.js"
    }
  }
}